{
  "temple": [
    {
      "name": "Las Vegas Temple",

      "address": ["27 Temple View Dr", "Las Vegas NV 89110-2920", "United States"],
      "phone": "(1) 702-452-5011",
      "image": "images/temples/las_vegas_temple.webp",
      "email": "https://www.churchofjesuschrist.org/temples",
      "services": [
        "Clothing rental available",
        "No cafeteria available",
        "No patron housing available",
        "Distribution center nearby"
      ],
      "history": "The Las Vegas Temple was dedicated on December 16th 1989 by Gordon B. Hinckley, becoming the 43rd temple overall. It was also the first temple in the state of Nevada.",
      "ordinanceSched": "All ordinances are available by appointment only.",
      "sessionSched": "All ordinances are available by appointment only.",
      "closureSched": [
        "Saturday, 2 April 2022",
        "Monday, 11 July 2022 - Monday, 25 July 2022",
        "Saturday, 1 October 2022",
        "Wednesday, 23 November 2022 - Thursday, 24 November 2022",
        "Saturday, 24 December 2022"
      ]
    },

    {
      "name": "Toronto Ontario Temple",
      "address": ["10060 Bramalea Rd", "Brampton ON L6R 1A1", "Canada"],
      "phone": "(1) 905-799-1122",
      "image": "images/temples/toronto-temple_flowers.webp",
      "email": "https://www.churchofjesuschrist.org/temples",
      "services": [
        "Clothing rental available",
        "No cafeteria available",
        "No patron housing available",
        "Distribution center nearby"
      ],

      "history": "On June 22, 1986, Thomas S. Monson, then a counselor in the First Presidency, created the LDS Church's 1,600th stake in Kitchener, Ontario, and announced a temple would be built in the Toronto area. Ground was broken to signify beginning of construction on 10 October 1987.",
      "ordinanceSched": "All ordinances are available by appointment only.",
      "sessionSched": "All ordinances are available by appointment only.",

      "closureSched": [
        "Saturday, 2 April 2022",
        "Friday, 1 July 2022",
        "Monday, 22 August 2022 - Monday, 5 September 2022",
        "Saturday, 1 October 2022",
        "Saturday, 24 December 2022",
        "Saturday, 31 December 2022"
      ]
    },
    {
      "name": "Salt Lake Temple",
      "address": ["50 W North Temple St", "Salt Lake City UT 84150-9709", "United States"],
      "phone": "(1) 801-240-2640",
      "image": "images/temples/salt_lake_temple.webp", 
      "email": "https://www.churchofjesuschrist.org/temples",
      "services": [
        "Clothing rental available",
        "No cafeteria available",
        "No patron housing available",
        "Distribution center nearby"
      ],
      "history": "As the world's largest Mormon temple, the 210-foot-tall Salt Lake Temple, with its granite edifice in a neo-Gothic style, took 40 years to build, from 1853 to 1893. With walls nine feet thick at the base and six feet thick at the top.",
      "ordinanceSched": "Temple closed during renovation",
      "sessionSched": "Temple closed during renovation",
      "closureSched": ["Temple closed during renovation"]
    },
    {
      "name": "Cedar City Temple",
      "address": ["280 South Cove Dr", "Cedar City UT 84720", "United States"],
      "phone": "(1) 435-572-4150",
      "image": "images/temples/cedar_city_utah_temple.webp",
      "email": "https://www.churchofjesuschrist.org/temples",
      "services": [
        "Clothing rental available",
        "No cafeteria available",
        "No patron housing available",
        "Distribution center nearby"
      ],
      "history": "The Cedar City Utah Temple was the seventeenth temple built in Utah. One of the great temple hymns, High on a Mountain Top, was written by Joel Hill Johnson while living in Enoch, Utah, a suburb of Cedar City. A youth cultural celebration was held the evening before the dedication of the Cedar City Utah Temple at the Centrum Arena on Saturday, December 9, 2017.",
      "ordinanceSched": "All ordinances are available by appointment only.",
      "sessionSched": "All ordinances are available by appointment only. ",
      "closureSched": [
        "Saturday, 2 April 2022",
        "Monday, 11 April 2022 - Monday, 25 April 2022",
        "Saturday, 1 October 2022",
        "Monday, 10 October 2022 - Monday, 24 October 2022",
        "Wednesday, 23 November 2022 - Thursday, 24 November 2022",
        "Saturday, 24 December 2022 - Sunday, 25 December 2022",
        "Saturday, 31 December 2022 - Sunday, 1 January 2023"
      ]
    }
  ]
}
